certbot_dns_ispconfig_ddns/__init__.py
certbot_dns_ispconfig_ddns/authenticator.py
certbot_dns_ispconfig_ddns/ispconfig_client.py
certbot_dns_ispconfig_ddns-1.0.9.dist-info/LICENSE
certbot_dns_ispconfig_ddns-1.0.9.dist-info/METADATA
certbot_dns_ispconfig_ddns-1.0.9.dist-info/WHEEL
certbot_dns_ispconfig_ddns-1.0.9.dist-info/entry_points.txt
certbot_dns_ispconfig_ddns-1.0.9.dist-info/RECORD
