Metadata-Version: 2.1
Name: certbot-dns-ispconfig-ddns
Version: 1.0.9
Summary: Obtain certificates using a DNS TXT record for ISPConfig domains with DDNS module tokens
Home-page: https://github.com/mhofer117/certbot-dns-ispconfig-ddns
License: Apache-2.0
Author: Marcel Hofer
Author-email: m.hofer117@gmail.com
Requires-Python: >=3.8,<4.0
Classifier: License :: OSI Approved :: Apache Software License
Classifier: Operating System :: OS Independent
Classifier: Programming Language :: Python :: 3
Classifier: Programming Language :: Python :: 3.8
Classifier: Programming Language :: Python :: 3.9
Classifier: Programming Language :: Python :: 3.10
Classifier: Programming Language :: Python :: 3.11
Classifier: Programming Language :: Python :: 3.12
Classifier: Topic :: Internet :: WWW/HTTP
Classifier: Topic :: Security
Classifier: Topic :: System :: Systems Administration
Classifier: Topic :: Utilities
Requires-Dist: certbot
Requires-Dist: requests
Project-URL: Repository, https://github.com/mhofer117/certbot-dns-ispconfig-ddns
